{
  "main": {
    "id": "2cc830fb6990ec4d",
    "type": "split",
    "children": [
      {
        "id": "276183d23792ffc8",
        "type": "tabs",
        "dimension": 50.58724832214765,
        "children": [
          {
            "id": "909fdfd41a46591a",
            "type": "leaf",
            "state": {
              "type": "markdown",
              "state": {
                "file": "session 1/kitchen.md",
                "mode": "source",
                "source": false
              },
              "icon": "lucide-file",
              "title": "kitchen"
            }
          },
          {
            "id": "655946c3f840cadf",
            "type": "leaf",
            "state": {
              "type": "markdown",
              "state": {
                "file": "session 2/room 2.md",
                "mode": "source",
                "source": false
              },
              "icon": "lucide-file",
              "title": "room 2"
            }
          }
        ],
        "currentTab": 1
      },
      {
        "id": "80e6fd3998b00e86",
        "type": "tabs",
        "dimension": 49.41275167785235,
        "children": [
          {
            "id": "95958e3bec347a4b",
            "type": "leaf",
            "state": {
              "type": "empty",
              "state": {},
              "icon": "lucide-file",
              "title": "New tab"
            }
          }
        ]
      }
    ],
    "direction": "vertical"
  },
  "left": {
    "id": "d453a2625d076ed0",
    "type": "split",
    "children": [
      {
        "id": "9a0fcba8691b0f18",
        "type": "tabs",
        "children": [
          {
            "id": "4d302985ccce1c56",
            "type": "leaf",
            "state": {
              "type": "file-explorer",
              "state": {
                "sortOrder": "alphabetical",
                "autoReveal": false
              },
              "icon": "lucide-folder-closed",
              "title": "Files"
            }
          },
          {
            "id": "2f307f79f9e3a0bd",
            "type": "leaf",
            "state": {
              "type": "search",
              "state": {
                "query": "",
                "matchingCase": false,
                "explainSearch": false,
                "collapseAll": false,
                "extraContext": false,
                "sortOrder": "alphabetical"
              },
              "icon": "lucide-search",
              "title": "Search"
            }
          },
          {
            "id": "c16f6def782fc01e",
            "type": "leaf",
            "state": {
              "type": "bookmarks",
              "state": {},
              "icon": "lucide-bookmark",
              "title": "Bookmarks"
            }
          }
        ]
      }
    ],
    "direction": "horizontal",
    "width": 300
  },
  "right": {
    "id": "54e7f35dace00706",
    "type": "split",
    "children": [
      {
        "id": "729bab01c26d69ed",
        "type": "tabs",
        "children": [
          {
            "id": "8a192a2e3fa002fb",
            "type": "leaf",
            "state": {
              "type": "backlink",
              "state": {
                "file": "solrana.md",
                "collapseAll": false,
                "extraContext": false,
                "sortOrder": "alphabetical",
                "showSearch": false,
                "searchQuery": "",
                "backlinkCollapsed": false,
                "unlinkedCollapsed": true
              },
              "icon": "links-coming-in",
              "title": "Backlinks for solrana"
            }
          },
          {
            "id": "f77561a19912b87e",
            "type": "leaf",
            "state": {
              "type": "outgoing-link",
              "state": {
                "file": "solrana.md",
                "linksCollapsed": false,
                "unlinkedCollapsed": true
              },
              "icon": "links-going-out",
              "title": "Outgoing links from solrana"
            }
          },
          {
            "id": "095ccd321eda0750",
            "type": "leaf",
            "state": {
              "type": "tag",
              "state": {
                "sortOrder": "frequency",
                "useHierarchy": true,
                "showSearch": false,
                "searchQuery": ""
              },
              "icon": "lucide-tags",
              "title": "Tags"
            }
          },
          {
            "id": "f8b17b38389426e2",
            "type": "leaf",
            "state": {
              "type": "outline",
              "state": {
                "file": "solrana.md",
                "followCursor": false,
                "showSearch": false,
                "searchQuery": ""
              },
              "icon": "lucide-list",
              "title": "Outline of solrana"
            }
          }
        ]
      }
    ],
    "direction": "horizontal",
    "width": 300,
    "collapsed": true
  },
  "left-ribbon": {
    "hiddenItems": {
      "switcher:Open quick switcher": false,
      "graph:Open graph view": false,
      "canvas:Create new canvas": false,
      "daily-notes:Open today's daily note": false,
      "templates:Insert template": false,
      "command-palette:Open command palette": false,
      "github-sync:Sync with Remote": false
    }
  },
  "active": "655946c3f840cadf",
  "lastOpenFiles": [
    "session 2/room 3.md",
    "session 2/room 2.md",
    "session 2/room 4.md",
    "session 2/caverns.md",
    "session 1/attempt to get past the people at the front.md",
    "session 1/weird guy encounter.md",
    "session 1/truck trip.md",
    "session 1/leave through the back door.md",
    "session 2",
    "session 1/intro.md",
    "session 1/kitchen.md",
    "session 1/gas station.md",
    "earth.md",
    "blahblahblah.md",
    "Pasted image 20250214140655.jpg",
    "Pasted image 20250208150032.jpg",
    "Pasted image 20250208150009.jpg",
    "session 1",
    "solrana.md",
    "README.md",
    "New folder",
    "space_cowboys/README.md",
    "space_cowboys"
  ]
}